README.md
setup.cfg
setup.py
ahtest_distributions/Binomialdistribution.py
ahtest_distributions/Gaussiandistribution.py
ahtest_distributions/Generaldistribution.py
ahtest_distributions/__init__.py
ahtest_distributions.egg-info/PKG-INFO
ahtest_distributions.egg-info/SOURCES.txt
ahtest_distributions.egg-info/dependency_links.txt
ahtest_distributions.egg-info/not-zip-safe
ahtest_distributions.egg-info/top_level.txt