Metadata-Version: 1.0
Name: ahtest-distributions
Version: 0.3
Summary: Gaussian distributions
Home-page: UNKNOWN
Author: Ahsan
Author-email: ahsan@ahsan.com
License: UNKNOWN
Platform: UNKNOWN
